Metadata-Version: 2.1
Name: api-jwt-2
Version: 1.3.1
Summary: Library for JWT encoding/decoding specifically adapted to use in APIs
Home-page: https://github.com/krystian-kulgawczuk-pr/api_jwt
Author: Greger Wedel
Author-email: greger@greger.io
License: Apache2
Platform: UNKNOWN
Classifier: Development Status :: 5 - Production/Stable
Classifier: Intended Audience :: Developers
Classifier: License :: OSI Approved :: Apache Software License
Classifier: Programming Language :: Python :: 2.7
Classifier: Programming Language :: Python :: 3
